Workbook

Sheet Cover
A1: FP&A Variance Pack
A2: Modeled B2B SaaS company — monthly budget vs. actual review
A4: Close month: September 2026 (latest closed month; 21 months of actuals, Jan 2025 – Sep 2026)
A5: Prepared by: Archit Chawla
A7: Contents
A8: PL_Summary — September 2026 and FY2026-to-date P&L: budget, actual, variance (live formulas)
A9: Variance_Detail — September line detail with flags, plus labor rate/volume decomposition
A10: Anomaly_Log — every flagged line-month from the two detection layers, with the validation scorecard
A11: Forecast — Q4 2026 rolling reforecast and the Dec-2025 backtest vs. budget
A12: Data_Budget / Data_Actual — the full monthly grids the summary formulas read
A13: Methodology — thresholds, sign conventions, and limitations
A15: The company is a modeled business built for this project; the structure, thresholds and
A16: workflow are a real FP&A close process. See Methodology.

Sheet Data_Budget
A1: Line | B1: 2025-01 | C1: 2025-02 | D1: 2025-03 | E1: 2025-04 | F1: 2025-05 | G1: 2025-06 | H1: 2025-07 | I1: 2025-08 | J1: 2025-09 | K1: 2025-10 | L1: 2025-11 | M1: 2025-12 | N1: 2026-01 | O1: 2026-02 | P1: 2026-03 | Q1: 2026-04 | R1: 2026-05 | S1: 2026-06 | T1: 2026-07 | U1: 2026-08 | V1: 2026-09 | W1: 2026-10 | X1: 2026-11 | Y1: 2026-12
A2: Subscription Revenue | B2: 2050000 | C2: 2093050 | D2: 2137004 | E2: 2181881.1 | F2: 2227700.6 | G2: 2274482.4 | H2: 2322246.5 | I2: 2371013.7 | J2: 2420804.9 | K2: 2471641.9 | L2: 2523546.3 | M2: 2576540.8 | N2: 2630648.2 | O2: 2685891.8 | P2: 2742295.5 | Q2: 2799883.7 | R2: 2858681.3 | S2: 2918713.6 | T2: 2980006.5 | U2: 3042586.7 | V2: 3106481 | W2: 3171717.1 | X2: 3238323.2 | Y2: 3306328
A3: Services Revenue | B3: 185000 | C3: 186850 | D3: 188718.5 | E3: 190605.69 | F3: 192511.74 | G3: 194436.86 | H3: 196381.23 | I3: 198345.04 | J3: 200328.49 | K3: 202331.78 | L3: 204355.09 | M3: 206398.64 | N3: 208462.63 | O3: 210547.26 | P3: 212652.73 | Q3: 214779.26 | R3: 216927.05 | S3: 219096.32 | T3: 221287.28 | U3: 223500.16 | V3: 225735.16 | W3: 227992.51 | X3: 230272.43 | Y3: 232575.16
A4: Cloud Hosting | B4: 385000 | C4: 393855 | D4: 402913.66 | E4: 412180.68 | F4: 421660.83 | G4: 431359.03 | H4: 441280.29 | I4: 451429.74 | J4: 461812.62 | K4: 472434.31 | L4: 483300.3 | M4: 494416.21 | N4: 505787.78 | O4: 517420.9 | P4: 529321.58 | Q4: 541495.98 | R4: 553950.39 | S4: 566691.24 | T4: 579725.14 | U4: 593058.82 | V4: 606699.17 | W4: 620653.26 | X4: 634928.28 | Y4: 649531.63
A5: Support Labor | B5: 268000 | C5: 271216 | D5: 274470.59 | E5: 277764.24 | F5: 281097.41 | G5: 284470.58 | H5: 287884.23 | I5: 291338.84 | J5: 294834.9 | K5: 298372.92 | L5: 301953.4 | M5: 305576.84 | N5: 309243.76 | O5: 312954.68 | P5: 316710.14 | Q5: 320510.66 | R5: 324356.79 | S5: 328249.07 | T5: 332188.06 | U5: 336174.32 | V5: 340208.41 | W5: 344290.91 | X5: 348422.4 | Y5: 352603.47
A6: Engineering Labor | B6: 742000 | C6: 752388 | D6: 762921.43 | E6: 773602.33 | F6: 784432.76 | G6: 795414.82 | H6: 806550.63 | I6: 817842.34 | J6: 829292.13 | K6: 840902.22 | L6: 852674.85 | M6: 864612.3 | N6: 876716.87 | O6: 888990.91 | P6: 901436.78 | Q6: 914056.9 | R6: 926853.69 | S6: 939829.65 | T6: 952987.26 | U6: 966329.08 | V6: 979857.69 | W6: 993575.7 | X6: 1007485.8 | Y6: 1021590.6
A7: Software & Tools | B7: 96000 | C7: 97152 | D7: 98317.82 | E7: 99497.64 | F7: 100691.61 | G7: 101899.91 | H7: 103122.71 | I7: 104360.18 | J7: 105612.5 | K7: 106879.85 | L7: 108162.41 | M7: 109460.36 | N7: 110773.88 | O7: 112103.17 | P7: 113448.41 | Q7: 114809.79 | R7: 116187.51 | S7: 117581.76 | T7: 118992.74 | U7: 120420.65 | V7: 121865.7 | W7: 123328.09 | X7: 124808.02 | Y7: 126305.72
A8: Sales & Marketing Labor | B8: 512000 | C8: 520192 | D8: 528515.07 | E8: 536971.31 | F8: 545562.85 | G8: 554291.86 | H8: 563160.53 | I8: 572171.1 | J8: 581325.84 | K8: 590627.05 | L8: 600077.08 | M8: 609678.32 | N8: 619433.17 | O8: 629344.1 | P8: 639413.6 | Q8: 649644.22 | R8: 660038.53 | S8: 670599.15 | T8: 681328.73 | U8: 692229.99 | V8: 703305.67 | W8: 714558.56 | X8: 725991.5 | Y8: 737607.36
A9: Marketing Programs | B9: 148000 | C9: 149184 | D9: 150377.47 | E9: 151580.49 | F9: 152793.14 | G9: 154015.48 | H9: 155247.6 | I9: 156489.59 | J9: 157741.5 | K9: 159003.43 | L9: 160275.46 | M9: 161557.67 | N9: 162850.13 | O9: 164152.93 | P9: 165466.15 | Q9: 166789.88 | R9: 168124.2 | S9: 169469.19 | T9: 170824.95 | U9: 172191.55 | V9: 173569.08 | W9: 174957.63 | X9: 176357.29 | Y9: 177768.15
A10: Customer Success Labor | B10: 196000 | C10: 198548 | D10: 201129.12 | E10: 203743.8 | F10: 206392.47 | G10: 209075.57 | H10: 211793.56 | I10: 214546.87 | J10: 217335.98 | K10: 220161.35 | L10: 223023.45 | M10: 225922.75 | N10: 228859.75 | O10: 231834.92 | P10: 234848.78 | Q10: 237901.81 | R10: 240994.54 | S10: 244127.47 | T10: 247301.12 | U10: 250516.04 | V10: 253772.75 | W10: 257071.79 | X10: 260413.72 | Y10: 263799.1
A11: G&A Labor | B11: 238000 | C11: 240380 | D11: 242783.8 | E11: 245211.64 | F11: 247663.75 | G11: 250140.39 | H11: 252641.8 | I11: 255168.21 | J11: 257719.9 | K11: 260297.09 | L11: 262900.07 | M11: 265529.07 | N11: 268184.36 | O11: 270866.2 | P11: 273574.86 | Q11: 276310.61 | R11: 279073.72 | S11: 281864.45 | T11: 284683.1 | U11: 287529.93 | V11: 290405.23 | W11: 293309.28 | X11: 296242.37 | Y11: 299204.8
A12: Legal & Professional | B12: 54000 | C12: 54216 | D12: 54432.86 | E12: 54650.6 | F12: 54869.2 | G12: 55088.67 | H12: 55309.03 | I12: 55530.27 | J12: 55752.39 | K12: 55975.4 | L12: 56199.3 | M12: 56424.09 | N12: 56649.79 | O12: 56876.39 | P12: 57103.9 | Q12: 57332.31 | R12: 57561.64 | S12: 57791.89 | T12: 58023.05 | U12: 58255.15 | V12: 58488.17 | W12: 58722.12 | X12: 58957.01 | Y12: 59192.84
A13: Facilities & Other | B13: 88000 | C13: 88440 | D13: 88882.2 | E13: 89326.61 | F13: 89773.24 | G13: 90222.11 | H13: 90673.22 | I13: 91126.59 | J13: 91582.22 | K13: 92040.13 | L13: 92500.33 | M13: 92962.83 | N13: 93427.65 | O13: 93894.79 | P13: 94364.26 | Q13: 94836.08 | R13: 95310.26 | S13: 95786.81 | T13: 96265.75 | U13: 96747.08 | V13: 97230.81 | W13: 97716.96 | X13: 98205.55 | Y13: 98696.58

Sheet Data_Actual
A1: Line | B1: 2025-01 | C1: 2025-02 | D1: 2025-03 | E1: 2025-04 | F1: 2025-05 | G1: 2025-06 | H1: 2025-07 | I1: 2025-08 | J1: 2025-09 | K1: 2025-10 | L1: 2025-11 | M1: 2025-12 | N1: 2026-01 | O1: 2026-02 | P1: 2026-03 | Q1: 2026-04 | R1: 2026-05 | S1: 2026-06 | T1: 2026-07 | U1: 2026-08 | V1: 2026-09 | W1: 2026-10 | X1: 2026-11 | Y1: 2026-12
A2: Subscription Revenue | B2: 2057496 | C2: 2066929.1 | D2: 2156248.7 | E2: 2206507.5 | F2: 2175544.8 | G2: 2238940.9 | H2: 2325809 | I2: 2362015.9 | J2: 2420316.9 | K2: 2446340.8 | L2: 2550176.8 | M2: 2600589 | N2: 2474768.6 | O2: 2558890.1 | P2: 2592219.3 | Q2: 2771012.7 | R2: 2871331 | S2: 2885129.1 | T2: 3011420 | U2: 3040763.8 | V2: 3099589.8
A3: Services Revenue | B3: 181220.84 | C3: 193702.96 | D3: 187843.62 | E3: 188156.43 | F3: 190478.05 | G3: 197541.88 | H3: 198534.22 | I3: 200800.94 | J3: 202917.66 | K3: 215331.48 | L3: 201863.5 | M3: 203226.86 | N3: 203373.39 | O3: 214438.04 | P3: 219855.1 | Q3: 214045.05 | R3: 211459.47 | S3: 213677.1 | T3: 225606.32 | U3: 228483.68 | V3: 229413.43
A4: Cloud Hosting | B4: 379875.58 | C4: 395683.76 | D4: 403853.95 | E4: 413983.46 | F4: 429009.78 | G4: 433288.03 | H4: 447272.12 | I4: 452039.88 | J4: 464483 | K4: 478399.16 | L4: 469215.43 | M4: 491255.2 | N4: 501029.61 | O4: 510809.53 | P4: 710651.89 | Q4: 557686.07 | R4: 544357.84 | S4: 577665.54 | T4: 560213.1 | U4: 589086.69 | V4: 608674.02
A5: Support Labor | B5: 270356.61 | C5: 274109.44 | D5: 277736.85 | E5: 276311.29 | F5: 279147.92 | G5: 288131.61 | H5: 287058.12 | I5: 285763.98 | J5: 289822.91 | K5: 294257.83 | L5: 304205.19 | M5: 306229.67 | N5: 312446.68 | O5: 310949.02 | P5: 317463.31 | Q5: 323518.29 | R5: 322851.71 | S5: 330498.11 | T5: 328889.8 | U5: 334343.58 | V5: 338260.35
A6: Engineering Labor | B6: 728690.3 | C6: 757883.88 | D6: 757549.68 | E6: 773747.31 | F6: 790089.47 | G6: 800742.49 | H6: 814600.63 | I6: 816634.16 | J6: 824026.56 | K6: 839896.69 | L6: 831093.64 | M6: 845844.43 | N6: 859322.38 | O6: 875692.76 | P6: 906842.35 | Q6: 793444.97 | R6: 811004.63 | S6: 843167.99 | T6: 947894.54 | U6: 977019.32 | V6: 966135.5
A7: Software & Tools | B7: 95506.95 | C7: 94844.59 | D7: 97484.5 | E7: 101587.85 | F7: 96343.44 | G7: 103006.6 | H7: 103735.61 | I7: 102810.04 | J7: 101794.46 | K7: 107072.58 | L7: 106730.63 | M7: 110097.08 | N7: 110834.4 | O7: 116592.28 | P7: 112769.55 | Q7: 111872.1 | R7: 116708.25 | S7: 118228.45 | T7: 123036.07 | U7: 122934.77 | V7: 122952.96
A8: Sales & Marketing Labor | B8: 523238.17 | C8: 510916.22 | D8: 523443.3 | E8: 529508.14 | F8: 542372.87 | G8: 542845.57 | H8: 568525.91 | I8: 570263.86 | J8: 568500.57 | K8: 581629.62 | L8: 602899.07 | M8: 617343.13 | N8: 637985.79 | O8: 656851.43 | P8: 643388.29 | Q8: 640001.51 | R8: 638930.04 | S8: 673292.05 | T8: 673020.53 | U8: 687917.15 | V8: 696848.3
A9: Marketing Programs | B9: 147374.89 | C9: 153954.82 | D9: 151085.97 | E9: 150859.11 | F9: 148045.91 | G9: 146277.67 | H9: 152982.66 | I9: 156237.09 | J9: 212617.96 | K9: 204319.82 | L9: 165000.73 | M9: 159137.71 | N9: 157061.08 | O9: 159400.13 | P9: 161866.14 | Q9: 177440.1 | R9: 163981.35 | S9: 173732.14 | T9: 166197.67 | U9: 177003.82 | V9: 175573.55
A10: Customer Success Labor | B10: 195539.48 | C10: 198426.6 | D10: 199153.67 | E10: 205107.07 | F10: 204983.89 | G10: 205231.91 | H10: 207733.67 | I10: 215102.3 | J10: 222483.88 | K10: 220689.71 | L10: 222626.56 | M10: 226891.37 | N10: 233343.12 | O10: 232597.83 | P10: 233401.19 | Q10: 241849.63 | R10: 242544.46 | S10: 249751.27 | T10: 247980.83 | U10: 245914.8 | V10: 248564.72
A11: G&A Labor | B11: 243893.81 | C11: 246595.02 | D11: 242130.03 | E11: 243802.21 | F11: 253092.96 | G11: 245986.64 | H11: 249251.11 | I11: 257630.56 | J11: 256194.43 | K11: 260277.1 | L11: 262255.53 | M11: 266873.6 | N11: 273846.33 | O11: 271234.25 | P11: 276217.34 | Q11: 267813.35 | R11: 278869.78 | S11: 278299.31 | T11: 279478.47 | U11: 309279.33 | V11: 288949.76
A12: Legal & Professional | B12: 55978.35 | C12: 51339.53 | D12: 54499.56 | E12: 53592.19 | F12: 54150.03 | G12: 57298.3 | H12: 56499.54 | I12: 58500.91 | J12: 55407.82 | K12: 54417.17 | L12: 55696.07 | M12: 56971.4 | N12: 57049.9 | O12: 54409.35 | P12: 57310.59 | Q12: 57855.71 | R12: 223358.04 | S12: 62130.54 | T12: 56042.74 | U12: 57585.48 | V12: 55064.41
A13: Facilities & Other | B13: 86960.36 | C13: 88998.24 | D13: 91025.78 | E13: 88024.08 | F13: 88598.75 | G13: 86347.45 | H13: 90378.23 | I13: 89190.3 | J13: 90612.48 | K13: 90426 | L13: 92325.95 | M13: 89694.77 | N13: 90686.4 | O13: 97893.29 | P13: 91934.53 | Q13: 92755.78 | R13: 98811.8 | S13: 101352.16 | T13: 94010.11 | U13: 96034.54 | V13: 97895.01

Sheet PL_Summary
A1: P&L Summary — variance vs. budget (live formulas from Data grids)
A3: Line | B3: Kind | C3: Sep-26 Budget | D3: Sep-26 Actual | E3: Sep Var $ | F3: Sep Var % | G3: F/U | H3: FYTD Budget | I3: FYTD Actual | J3: FYTD Var $ | K3: FYTD Var % | L3: F/U
A4: Subscription Revenue | B4: revenue | C4: ='Data_Budget'!V2 | D4: ='Data_Actual'!V2 | E4: =D4-C4 | F4: =IF(C4=0,0,E4/C4) | G4: U | H4: =SUM('Data_Budget'!N2:V2) | I4: =SUM('Data_Actual'!N2:V2) | J4: =I4-H4 | K4: =IF(H4=0,0,J4/H4) | L4: U
A5: Services Revenue | B5: revenue | C5: ='Data_Budget'!V3 | D5: ='Data_Actual'!V3 | E5: =D5-C5 | F5: =IF(C5=0,0,E5/C5) | G5: F | H5: =SUM('Data_Budget'!N3:V3) | I5: =SUM('Data_Actual'!N3:V3) | J5: =I5-H5 | K5: =IF(H5=0,0,J5/H5) | L5: F
A6: Cloud Hosting | B6: cost | C6: ='Data_Budget'!V4 | D6: ='Data_Actual'!V4 | E6: =D6-C6 | F6: =IF(C6=0,0,E6/C6) | G6: U | H6: =SUM('Data_Budget'!N4:V4) | I6: =SUM('Data_Actual'!N4:V4) | J6: =I6-H6 | K6: =IF(H6=0,0,J6/H6) | L6: U
A7: Support Labor | B7: cost | C7: ='Data_Budget'!V5 | D7: ='Data_Actual'!V5 | E7: =D7-C7 | F7: =IF(C7=0,0,E7/C7) | G7: F | H7: =SUM('Data_Budget'!N5:V5) | I7: =SUM('Data_Actual'!N5:V5) | J7: =I7-H7 | K7: =IF(H7=0,0,J7/H7) | L7: F
A8: Engineering Labor | B8: cost | C8: ='Data_Budget'!V6 | D8: ='Data_Actual'!V6 | E8: =D8-C8 | F8: =IF(C8=0,0,E8/C8) | G8: F | H8: =SUM('Data_Budget'!N6:V6) | I8: =SUM('Data_Actual'!N6:V6) | J8: =I8-H8 | K8: =IF(H8=0,0,J8/H8) | L8: F
A9: Software & Tools | B9: cost | C9: ='Data_Budget'!V7 | D9: ='Data_Actual'!V7 | E9: =D9-C9 | F9: =IF(C9=0,0,E9/C9) | G9: U | H9: =SUM('Data_Budget'!N7:V7) | I9: =SUM('Data_Actual'!N7:V7) | J9: =I9-H9 | K9: =IF(H9=0,0,J9/H9) | L9: U
A10: Sales & Marketing Labor | B10: cost | C10: ='Data_Budget'!V8 | D10: ='Data_Actual'!V8 | E10: =D10-C10 | F10: =IF(C10=0,0,E10/C10) | G10: F | H10: =SUM('Data_Budget'!N8:V8) | I10: =SUM('Data_Actual'!N8:V8) | J10: =I10-H10 | K10: =IF(H10=0,0,J10/H10) | L10: U
A11: Marketing Programs | B11: cost | C11: ='Data_Budget'!V9 | D11: ='Data_Actual'!V9 | E11: =D11-C11 | F11: =IF(C11=0,0,E11/C11) | G11: U | H11: =SUM('Data_Budget'!N9:V9) | I11: =SUM('Data_Actual'!N9:V9) | J11: =I11-H11 | K11: =IF(H11=0,0,J11/H11) | L11: F
A12: Customer Success Labor | B12: cost | C12: ='Data_Budget'!V10 | D12: ='Data_Actual'!V10 | E12: =D12-C12 | F12: =IF(C12=0,0,E12/C12) | G12: F | H12: =SUM('Data_Budget'!N10:V10) | I12: =SUM('Data_Actual'!N10:V10) | J12: =I12-H12 | K12: =IF(H12=0,0,J12/H12) | L12: U
A13: G&A Labor | B13: cost | C13: ='Data_Budget'!V11 | D13: ='Data_Actual'!V11 | E13: =D13-C13 | F13: =IF(C13=0,0,E13/C13) | G13: F | H13: =SUM('Data_Budget'!N11:V11) | I13: =SUM('Data_Actual'!N11:V11) | J13: =I13-H13 | K13: =IF(H13=0,0,J13/H13) | L13: U
A14: Legal & Professional | B14: cost | C14: ='Data_Budget'!V12 | D14: ='Data_Actual'!V12 | E14: =D14-C14 | F14: =IF(C14=0,0,E14/C14) | G14: F | H14: =SUM('Data_Budget'!N12:V12) | I14: =SUM('Data_Actual'!N12:V12) | J14: =I14-H14 | K14: =IF(H14=0,0,J14/H14) | L14: U
A15: Facilities & Other | B15: cost | C15: ='Data_Budget'!V13 | D15: ='Data_Actual'!V13 | E15: =D15-C15 | F15: =IF(C15=0,0,E15/C15) | G15: U | H15: =SUM('Data_Budget'!N13:V13) | I15: =SUM('Data_Actual'!N13:V13) | J15: =I15-H15 | K15: =IF(H15=0,0,J15/H15) | L15: U
A16: Total Revenue | C16: =C4+C5 | D16: =D4+D5 | E16: =E4+E5 | F16: =IF(C16=0,0,E16/C16) | H16: =H4+H5 | I16: =I4+I5 | J16: =J4+J5 | K16: =IF(H16=0,0,J16/H16)
A17: Total Costs | C17: =C6+C7+C8+C9+C10+C11+C12+C13+C14+C15 | D17: =D6+D7+D8+D9+D10+D11+D12+D13+D14+D15 | E17: =E6+E7+E8+E9+E10+E11+E12+E13+E14+E15 | F17: =IF(C17=0,0,E17/C17) | H17: =H6+H7+H8+H9+H10+H11+H12+H13+H14+H15 | I17: =I6+I7+I8+I9+I10+I11+I12+I13+I14+I15 | J17: =J6+J7+J8+J9+J10+J11+J12+J13+J14+J15 | K17: =IF(H17=0,0,J17/H17)
A18: Operating Result | C18: =C16-C17 | D18: =D16-D17 | E18: =E16-E17 | F18: =IF(C16=0,0,E18/C16) | H18: =H16-H17 | I18: =I16-I17 | J18: =J16-J17 | K18: =IF(H16=0,0,J18/H16)

Sheet Variance_Detail
A1: September 2026 — line detail and flags
A3: Line | B3: Dept | C3: Budget | D3: Actual | E3: Var $ | F3: Var % | G3: F/U | H3: Tier | I3: Materiality | J3: Z-flag | K3: Z
A4: Engineering Labor | B4: R&D | C4: 979857.69 | D4: 966135.5 | E4: -13722.19 | F4: -0.014 | G4: F | K4: 0.64
A5: Subscription Revenue | B5: Revenue | C5: 3106481 | D5: 3099589.8 | E5: -6891.26 | F5: -0.0022 | G5: U | K5: 0.35
A6: Sales & Marketing Labor | B6: S&M | C6: 703305.67 | D6: 696848.3 | E6: -6457.37 | F6: -0.0092 | G6: F | K6: 0
A7: Customer Success Labor | B7: CS | C7: 253772.75 | D7: 248564.72 | E7: -5208.03 | F7: -0.0205 | G7: F | K7: -1.63
A8: Services Revenue | B8: Revenue | C8: 225735.16 | D8: 229413.43 | E8: 3678.27 | F8: 0.0163 | G8: F | K8: 0.5
A9: Legal & Professional | B9: G&A | C9: 58488.17 | D9: 55064.41 | E9: -3423.76 | F9: -0.0585 | G9: F | K9: -0.47
A10: Marketing Programs | B10: S&M | C10: 173569.08 | D10: 175573.55 | E10: 2004.47 | F10: 0.0115 | G10: U | K10: 0.12
A11: Cloud Hosting | B11: COGS | C11: 606699.17 | D11: 608674.02 | E11: 1974.85 | F11: 0.0033 | G11: U | K11: -0.37
A12: Support Labor | B12: COGS | C12: 340208.41 | D12: 338260.35 | E12: -1948.06 | F12: -0.0057 | G12: F | K12: -0.72
A13: G&A Labor | B13: G&A | C13: 290405.23 | D13: 288949.76 | E13: -1455.47 | F13: -0.005 | G13: F | K13: -0.23
A14: Software & Tools | B14: R&D | C14: 121865.7 | D14: 122952.96 | E14: 1087.26 | F14: 0.0089 | G14: U | K14: 0.16
A15: Facilities & Other | B15: G&A | C15: 97230.81 | D15: 97895.01 | E15: 664.2 | F15: 0.0068 | G15: U | K15: 0.11
A17: Labor decomposition — FY2026 to date (Jan–Sep): volume = headcount effect, rate = cost per head
A18: Line | B18: HC Budget (avg) | C18: HC Actual (avg) | D18: Volume var $ | E18: Rate var $ | F18: Total var $
A19: Customer Success Labor | B19: 32 | C19: 31.8 | D19: -12052 | E19: 17843 | F19: 5791
A20: Engineering Labor | B20: 107.5 | C20: 103.8 | D20: -284800 | E20: -81735 | F20: -366534
A21: G&A Labor | B21: 28.1 | C21: 28.3 | D21: 16842 | E21: -5346 | F21: 11495
A22: Sales & Marketing Labor | B22: 73.6 | C22: 74.1 | D22: 40412 | E22: -37514 | F22: 2898
A23: Support Labor | B23: 41.2 | C23: 41.3 | D23: 7883 | E23: -9258 | F23: -1375

Sheet Anomaly_Log
A1: Anomaly log — all flagged line-months (Jan 2025 – Sep 2026)
A2: Validation vs. ground truth: 10 of 11 planted event line-months caught (recall 91%); 20 of 252 line-months flagged for review; 10 false positives. Materiality layer alone: 9 caught, 0 false positives. Statistical layer adds recall at the cost of review volume.
A4: Month | B4: Line | C4: Kind | D4: Tier | E4: Budget | F4: Actual | G4: Var $ | H4: Var % | I4: F/U | J4: Planted event
A5: 2025-05 | B5: Marketing Programs | C5: cost | D5: Watch | E5: 152793.14 | F5: 148045.91 | G5: -4747.23 | H5: -0.0311 | I5: F
A6: 2025-05 | B6: Software & Tools | C6: cost | D6: Watch | E6: 100691.61 | F6: 96343.44 | G6: -4348.17 | H6: -0.0432 | I6: F
A7: 2025-06 | B7: Facilities & Other | C7: cost | D7: Watch | E7: 90222.11 | F7: 86347.45 | G7: -3874.66 | H7: -0.0429 | I7: F
A8: 2025-06 | B8: Marketing Programs | C8: cost | D8: Watch | E8: 154015.48 | F8: 146277.67 | G8: -7737.81 | H8: -0.0502 | I8: F
A9: 2025-09 | B9: Marketing Programs | C9: cost | D9: Alert | E9: 157741.5 | F9: 212617.96 | G9: 54876.46 | H9: 0.3479 | I9: U | J9: Yes
A10: 2025-10 | B10: Marketing Programs | C10: cost | D10: Alert | E10: 159003.43 | F10: 204319.82 | G10: 45316.39 | H10: 0.285 | I10: U | J10: Yes
A11: 2025-10 | B11: Services Revenue | C11: revenue | D11: Watch | E11: 202331.78 | F11: 215331.48 | G11: 12999.7 | H11: 0.0642 | I11: F
A12: 2026-01 | B12: Subscription Revenue | C12: revenue | D12: Alert | E12: 2630648.2 | F12: 2474768.6 | G12: -155879.52 | H12: -0.0593 | I12: U | J12: Yes
A13: 2026-02 | B13: Facilities & Other | C13: cost | D13: Watch | E13: 93894.79 | F13: 97893.29 | G13: 3998.5 | H13: 0.0426 | I13: U
A14: 2026-02 | B14: Sales & Marketing Labor | C14: cost | D14: Watch | E14: 629344.1 | F14: 656851.43 | G14: 27507.33 | H14: 0.0437 | I14: U
A15: 2026-02 | B15: Software & Tools | C15: cost | D15: Watch | E15: 112103.17 | F15: 116592.28 | G15: 4489.11 | H15: 0.04 | I15: U
A16: 2026-03 | B16: Cloud Hosting | C16: cost | D16: Alert | E16: 529321.58 | F16: 710651.89 | G16: 181330.31 | H16: 0.3426 | I16: U | J16: Yes
A17: 2026-03 | B17: Subscription Revenue | C17: revenue | D17: Alert | E17: 2742295.5 | F17: 2592219.3 | G17: -150076.22 | H17: -0.0547 | I17: U | J17: Yes
A18: 2026-04 | B18: Engineering Labor | C18: cost | D18: Alert | E18: 914056.9 | F18: 793444.97 | G18: -120611.93 | H18: -0.132 | I18: F | J18: Yes
A19: 2026-04 | B19: G&A Labor | C19: cost | D19: Watch | E19: 276310.61 | F19: 267813.35 | G19: -8497.26 | H19: -0.0308 | I19: F
A20: 2026-05 | B20: Engineering Labor | C20: cost | D20: Alert | E20: 926853.69 | F20: 811004.63 | G20: -115849.06 | H20: -0.125 | I20: F | J20: Yes
A21: 2026-05 | B21: Legal & Professional | C21: cost | D21: Alert | E21: 57561.64 | F21: 223358.04 | G21: 165796.4 | H21: 2.8803 | I21: U | J21: Yes
A22: 2026-05 | B22: Sales & Marketing Labor | C22: cost | D22: Watch | E22: 660038.53 | F22: 638930.04 | G22: -21108.49 | H22: -0.032 | I22: F
A23: 2026-06 | B23: Engineering Labor | C23: cost | D23: Alert | E23: 939829.65 | F23: 843167.99 | G23: -96661.66 | H23: -0.1029 | I23: F | J23: Yes
A24: 2026-08 | B24: G&A Labor | C24: cost | D24: Watch | E24: 287529.93 | F24: 309279.33 | G24: 21749.4 | H24: 0.0756 | I24: U | J24: Yes
A26: Missed by both layers:
A27: 2026-02 — Subscription Revenue: var $-127,002 (-4.7%), just under the 5% materiality bar

Sheet Forecast
A1: Rolling reforecast — Q4 2026 (trailing-6-month median var% run-rate, clipped at ±15%)
A3: Line | B3: Oct-26 | C3: Nov-26 | D3: Dec-26 | E3: Q4 Total
A4: Subscription Revenue | B4: 3167249 | C4: 3233761.2 | D4: 3301670.2 | E4: 9702680.5
A5: Services Revenue | B5: 229460.35 | C5: 231754.95 | D5: 234072.5 | E5: 695287.8
A6: Cloud Hosting | B6: 619584.92 | C6: 633835.37 | D6: 648413.58 | E6: 1901833.9
A7: Support Labor | B7: 342554.65 | C7: 346665.31 | D7: 350825.29 | E7: 1040045.2
A8: Engineering Labor | B8: 935523.82 | C8: 948621.16 | D8: 961901.85 | E8: 2846046.8
A9: Software & Tools | B9: 124217.39 | C9: 125707.99 | D9: 127216.49 | E9: 377141.87
A10: Sales & Marketing Labor | B10: 706921.51 | C10: 718232.26 | D10: 729723.97 | E10: 2154877.7
A11: Marketing Programs | B11: 178168.39 | C11: 179593.73 | D11: 181030.49 | E11: 538792.61
A12: Customer Success Labor | B12: 258251.73 | C12: 261609 | D12: 265009.92 | E12: 784870.65
A13: G&A Labor | B13: 290719.32 | C13: 293626.51 | D13: 296562.78 | E13: 880908.61
A14: Legal & Professional | B14: 58652.64 | C14: 58887.26 | D14: 59122.81 | E14: 176662.71
A15: Facilities & Other | B15: 97690.88 | C15: 98179.34 | D15: 98670.24 | E15: 294540.46
A17: Backtest — forecast made at Dec 2025 for Jan–Sep 2026: reforecast MAPE 3.2% vs. budget 3.2%. The reforecast wins on stable run-rate lines and cannot anticipate one-off events; overall it ties the budget.
A19: Line | B19: Reforecast MAPE | C19: Budget MAPE | D19: Winner
A20: Cloud Hosting | B20: 0.0437 | C20: 0.0431 | D20: Budget
A21: Customer Success Labor | B21: 0.0121 | C21: 0.0129 | D21: Reforecast
A22: Engineering Labor | B22: 0.0511 | C22: 0.0535 | D22: Reforecast
A23: Facilities & Other | B23: 0.0272 | C23: 0.0276 | D23: Reforecast
A24: G&A Labor | B24: 0.0189 | C24: 0.019 | D24: Reforecast
A25: Legal & Professional | B25: 0.1096 | C25: 0.1096 | D25: Budget
A26: Marketing Programs | B26: 0.0319 | C26: 0.0295 | D26: Budget
A27: Sales & Marketing Labor | B27: 0.0175 | C27: 0.0175 | D27: Budget
A28: Services Revenue | B28: 0.0198 | C28: 0.0208 | D28: Reforecast
A29: Software & Tools | B29: 0.019 | C29: 0.0159 | D29: Budget
A30: Subscription Revenue | B30: 0.0237 | C30: 0.0234 | D30: Budget
A31: Support Labor | B31: 0.0083 | C31: 0.0068 | D31: Budget

Sheet Methodology
A1: Methodology & verification notes
A3: Company: a modeled B2B SaaS business (~$30M FY2025 revenue plan) built for this project. Budget and actuals are
A4: generated from stated plan assumptions; six operating events were planted in the actuals as ground truth so the
A5: detection layer can be scored honestly. The workflow, thresholds and pack structure are a real FP&A close process.
A7: Materiality (Alert): |variance| >= $25,000 AND >= 5% of budget — fixed before seeing results.
A8: Statistical (Watch): |z| >= 2.0 on variance % vs. the line's own trailing 6 months, with a 3% actionability floor.
A9: Sign convention: revenue variance is favorable when actual > budget; cost variance is favorable when actual < budget.
A10: Labor decomposition: volume = (actual HC - budget HC) x budget cost/head; rate = (actual - budget cost/head) x actual HC.
A11: The two sum exactly to the labor variance. Reforecast: trailing-6-month median var% applied to budget, clipped at +/-15%.
A13: Limitations
A14: - A run-rate reforecast cannot anticipate one-off events (legal costs, freezes); the backtest shows it ties the budget overall.
A15: - The statistical layer trades precision for recall: about 8% of line-months are flagged for human review.
... A18: - Modeled data: magnitudes are realistic for a growth-stage SaaS P&L but are not a real company's financials.
